ai_debugger/__init__.py
ai_debugger/config.py
ai_debugger/debugger.py
ai_debugger/llm_analyzer.py
ai_debugger/pylint_analyzer.py
ai_debugger/runtime_err_checker.py
ai_debugger/static_analyzer.py
ai_debugger/syntax_checker.py
ai_debugger/utils.py
tests/__init__.py
tests/test_config.py
tests/test_syntax_checker.py
ai_debugger-0.1.0.dist-info/LICENSE
ai_debugger-0.1.0.dist-info/METADATA
ai_debugger-0.1.0.dist-info/WHEEL
ai_debugger-0.1.0.dist-info/entry_points.txt
ai_debugger-0.1.0.dist-info/top_level.txt
ai_debugger-0.1.0.dist-info/RECORD
